Pipeline_Generation/Estimate_after_profit.py
Pipeline_Generation/MCTS.py
Pipeline_Generation/MCTS_DATA.py
Pipeline_Generation/MetaFeature.py
Pipeline_Generation/User_Operation.py
Pipeline_Generation/__init__.py
Search_Space/__init__.py
Search_Space/classifier.py
Search_Space/duplicate_detector.py
Search_Space/encoding.py
Search_Space/feature_selector.py
Search_Space/imputer.py
Search_Space/normalizer.py
Search_Space/outlier_detector.py
Search_Space/regressor.py
ASDPP-0.1.0.dist-info/METADATA
ASDPP-0.1.0.dist-info/WHEEL
ASDPP-0.1.0.dist-info/top_level.txt
ASDPP-0.1.0.dist-info/RECORD
